{
  "step_00030000": {
    "step": 30000,
    "saved_at": "2026-03-28T01:11:46.077743",
    "size_bytes": 0,
    "path": "outputs/replay_buffers/sac/recon_phase2/step_00030000.pt"
  },
  "step_00040000": {
    "step": 40000,
    "saved_at": "2026-03-28T01:17:38.121665",
    "size_bytes": 0,
    "path": "outputs/replay_buffers/sac/recon_phase2/step_00040000.pt"
  },
  "step_00050000": {
    "step": 50000,
    "saved_at": "2026-03-28T01:23:43.196525",
    "size_bytes": 0,
    "path": "outputs/replay_buffers/sac/recon_phase2/step_00050000.pt"
  }
}